ytml/__init__.py
ytml-1.0.2.dist-info/METADATA
ytml-1.0.2.dist-info/WHEEL
ytml-1.0.2.dist-info/entry_points.txt
ytml-1.0.2.dist-info/RECORD
